analyser/.gitignore
analyser/app.py
analyser/common/config.py
analyser/common/devicecontroller.py
analyser/common/measurementcontroller.py
analyser/common/signal.py
analyser/common/targetcontroller.py
analyser/common/targetstatecontroller.py
analyser/common/uploadcontroller.py
analyser/resources/analyse.py
analyser/resources/measurement.py
analyser/resources/measurementdevices.py
analyser/resources/measurements.py
analyser/resources/state.py
analyser/resources/target.py
analyser/resources/targets.py
analyser/resources/timeseries.py
analyser/resources/upload.py
analyser/ui/android-chrome-192x192.png
analyser/ui/android-chrome-384x384.png
analyser/ui/apple-touch-icon.png
analyser/ui/asset-manifest.json
analyser/ui/browserconfig.xml
analyser/ui/favicon-16x16.png
analyser/ui/favicon-32x32.png
analyser/ui/favicon.ico
analyser/ui/index.html
analyser/ui/manifest.json
analyser/ui/mstile-150x150.png
analyser/ui/safari-pinned-tab.svg
analyser/ui/service-worker.js
analyser/ui/vibe-100x100.png
analyser/ui/vibe-24x24.png
analyser/ui/static/css/main.709bc9dd.css
analyser/ui/static/css/main.709bc9dd.css.map
analyser/ui/static/js/main.d3175f3d.js
analyser/ui/static/js/main.d3175f3d.js.map
analyser/ui/static/media/fontawesome-webfont.674f50d2.eot
analyser/ui/static/media/fontawesome-webfont.912ec66d.svg
analyser/ui/static/media/fontawesome-webfont.af7ae505.woff2
analyser/ui/static/media/fontawesome-webfont.b06871f2.ttf
analyser/ui/static/media/fontawesome-webfont.fee66e71.woff
analyser/ui/static/media/glyphicons-halflings-regular.448c34a5.woff2
analyser/ui/static/media/glyphicons-halflings-regular.89889688.svg
analyser/ui/static/media/glyphicons-halflings-regular.e18bbf61.ttf
analyser/ui/static/media/glyphicons-halflings-regular.f4769f9b.eot
analyser/ui/static/media/glyphicons-halflings-regular.fa277232.woff
core/BaseConfig.py
core/handler.py
core/httpclient.py
core/interface.py
core/reactor.py
vibe_analyser-0.4.1.dist-info/DESCRIPTION.rst
vibe_analyser-0.4.1.dist-info/METADATA
vibe_analyser-0.4.1.dist-info/RECORD
vibe_analyser-0.4.1.dist-info/WHEEL
vibe_analyser-0.4.1.dist-info/entry_points.txt
vibe_analyser-0.4.1.dist-info/metadata.json
vibe_analyser-0.4.1.dist-info/top_level.txt
