Metadata-Version: 2.0
Name: vibe-analyser
Version: 0.4.1
Summary: A vibration analysis and data acquisition suite for the rpi
Home-page: http://github.com/3ll3d00d/vibe
Author: Matt Khan
Author-email: mattkhan+vibe@gmail.com
License: MIT
Platform: UNKNOWN
Classifier: Development Status :: 3 - Alpha
Classifier: Framework :: Flask
Classifier: License :: OSI Approved :: MIT License
Classifier: Programming Language :: Python :: 3.4
Classifier: Programming Language :: Python :: 3.5
Classifier: Intended Audience :: End Users/Desktop
Requires-Dist: cffi
Requires-Dist: flask
Requires-Dist: flask-restful
Requires-Dist: librosa
Requires-Dist: numpy
Requires-Dist: pysoundfile
Requires-Dist: pyyaml
Requires-Dist: requests
Requires-Dist: scipy
Requires-Dist: twisted
Requires-Dist: typing
